README.md
setup.cfg
setup.py
distributions_wge073/Binomialdistribution.py
distributions_wge073/Gaussiandistribution.py
distributions_wge073/Generaldistribution.py
distributions_wge073/__init__.py
distributions_wge073.egg-info/PKG-INFO
distributions_wge073.egg-info/SOURCES.txt
distributions_wge073.egg-info/dependency_links.txt
distributions_wge073.egg-info/not-zip-safe
distributions_wge073.egg-info/top_level.txt