Metadata-Version: 1.0
Name: distributions-wge073
Version: 0.11
Summary: Gaussian distributions
Home-page: UNKNOWN
Author: Wen Ge
Author-email: ng.wge073@gmail.com
License: UNKNOWN
Platform: UNKNOWN
